{
  "addedAnime": [],
  "removedAnime": [],
  "addedEpisodes": [],
  "removedEpisodes": [],
  "addedUrls": [],
  "updatedUrls": [
    {
      "animeTitle": "Zombieland Saga Revenge",
      "episode": 1,
      "page": "1",
      "url": "1",
      "oldTime": -31539360000,
      "newTime": -31539420000
    },
    {
      "animeTitle": "Suisei no Gargantia",
      "episode": 1,
      "page": "AnimeFenix",
      "url": "https://animefenix2.tv/ver/suisei-no-gargantia-1",
      "oldTime": -31539540000,
      "newTime": -31539480000
    }
  ],
  "removedUrls": []
}